Metadata-Version: 2.1
Name: naumen_service_desk_client
Version: 1.0.0
Summary: Execute API calls to Naumen Service Desk from python code
Home-page: https://github.com/ErilovNikita/naumen-service-desk-client.git
Author-email: minitwiks@gmail.com
License: MIT
License-File: LICENSE
Requires-Dist: requests==2.32.3
Requires-Dist: urllib3==2.2.3
Requires-Dist: pydantic==2.9.2
